{"timestamp":1649139758013,"status":"200 OK","responseCode":"MST001","attrs":{"data":{"daughter":{"category":"relationship","value":"Daughter","key":"daughter","id":6},"father":{"category":"relationship","value":"Father","key":"father","id":1},"husband":{"category":"relationship","value":"Husband","key":"husband","id":240},"mother":{"category":"relationship","value":"Mother","key":"mother","id":2},"others":{"category":"relationship","value":"Others","key":"others","id":239},"son":{"category":"relationship","value":"Son","key":"son","id":5},"wife":{"category":"relationship","value":"Wife","key":"wife","id":241}}},"message":"Success"}